nanaimo/__init__.py
nanaimo/__main__.py
nanaimo/cli.py
nanaimo/config.py
nanaimo/display.py
nanaimo/fixtures.py
nanaimo/version.py
nanaimo/builtin/__init__.py
nanaimo/builtin/nanaimo_bar.py
nanaimo/builtin/nanaimo_cmd.py
nanaimo/builtin/nanaimo_gather.py
nanaimo/builtin/nanaimo_scp.py
nanaimo/builtin/nanaimo_serial_watch.py
nanaimo/builtin/nanaimo_ssh.py
nanaimo/connections/__init__.py
nanaimo/connections/uart.py
nanaimo/instruments/__init__.py
nanaimo/instruments/bkprecision/__init__.py
nanaimo/instruments/jlink/__init__.py
nanaimo/instruments/saleae/__init__.py
nanaimo/instruments/ykush/__init__.py
nanaimo/parsers/__init__.py
nanaimo/parsers/imu.py
nanaimo/parsers/gtest/__init__.py
nanaimo/pytest/__init__.py
nanaimo/pytest/hooks.py
nanaimo/pytest/plugin.py
nanaimo-0.2.5.dist-info/LICENSE.rst
nanaimo-0.2.5.dist-info/METADATA
nanaimo-0.2.5.dist-info/WHEEL
nanaimo-0.2.5.dist-info/entry_points.txt
nanaimo-0.2.5.dist-info/top_level.txt
nanaimo-0.2.5.dist-info/RECORD
