Metadata-Version: 2.1
Name: nanaimo
Version: 0.2.5
Summary: Framework for automating tests involving hardware test fixtures.
Home-page: https://github.com/thirtytwobits/nanaimo
Author: Amazon.com
Author-email: dixonsco@amazon.com
License: MIT
Keywords: ci,hil,test
Platform: UNKNOWN
Classifier: Development Status :: 3 - Alpha
Classifier: Environment :: Console
Classifier: Environment :: Plugins
Classifier: Framework :: Pytest
Classifier: Intended Audience :: Developers
Classifier: License :: OSI Approved :: MIT License
Classifier: Programming Language :: Python
Classifier: Programming Language :: Python :: 3
Classifier: Programming Language :: Python :: 3.5
Classifier: Programming Language :: Python :: 3.6
Classifier: Programming Language :: Python :: 3.7
Classifier: Programming Language :: Python :: 3.8
Classifier: Programming Language :: Python :: 3 :: Only
Classifier: Topic :: Scientific/Engineering
Classifier: Topic :: Software Development :: Embedded Systems
Classifier: Topic :: Software Development :: Libraries
Classifier: Topic :: Software Development :: Build Tools
Classifier: Typing :: Typed
Requires-Python: >=3.5
Requires-Dist: pyserial
Requires-Dist: pytest
Requires-Dist: pytest-asyncio
